CHANGES.txt
LICENSE.txt
MANIFEST.in
README.rst
setup.py
Blend.egg-info/PKG-INFO
Blend.egg-info/SOURCES.txt
Blend.egg-info/dependency_links.txt
Blend.egg-info/top_level.txt
bin/blend
bin/blend.bat
blend/Analysis.py
blend/Analyzer.py
blend/Application.py
blend/Configuration.py
blend/JSLintAnalyzer.py
blend/Minification.py
blend/Minifier.py
blend/Paths.py
blend/Requirement.py
blend/Resource.py
blend/Result.py
blend/SizeAnalyzer.py
blend/YUICompressorMinifier.py
blend/__init__.py
blend/helpers.py
blend/run_tests.py
blend/lib/js.jar
blend/lib/js_LICENSE.TXT
blend/lib/jslint.js
blend/lib/yuicompressor-2.4.6.jar
blend/lib/yuicompressor_LICENSE.TXT
blend/test/TestAnalyzer.py
blend/test/TestApplication.py
blend/test/TestBlend.py
blend/test/TestConfiguration.py
blend/test/TestJSLintAnalyzer.py
blend/test/TestMinification.py
blend/test/TestMinifier.py
blend/test/TestPaths.py
blend/test/TestRequirement.py
blend/test/TestResource.py
blend/test/TestResult.py
blend/test/TestSizeAnalyzer.py
blend/test/TestYUICompressorMinifier.py
blend/test/__init__.py
blend/test/helpers.py
docs/_build/html/_sources/index.txt