Metadata-Version: 1.1
Name: Blend
Version: 0.1.5
Summary: A cross-platform tool for merging and processing client-side assets for a web application.
Home-page: http://github.com/azavea/blend
Author: Justin Walgran
Author-email: jwalgran@azavea.com
License: LICENSE.txt
Keywords: javascript css html build
Platform: UNKNOWN
Classifier: Development Status :: 4 - Beta
Classifier: Intended Audience :: Developers
Classifier: License :: OSI Approved :: MIT License
Classifier: Programming Language :: Python
Classifier: Topic :: Software Development :: Build Tools
